[
  {
    "id": 135403,
    "name": "Alfonsine",
    "state_id": 1707,
    "state_code": "RA",
    "country_id": 107,
    "country_code": "IT",
    "latitude": "44.50768000",
    "longitude": "12.03743000",
    "native": null,
    "timezone": "Europe/Rome",
    "translations": {}
  },
  {
    "id": 135748,
    "name": "Bagnacavallo",
    "state_id": 1707,
    "state_code": "RA",
    "country_id": 107,
    "country_code": "IT",
    "latitude": "44.41402000",
    "longitude": "11.97813000",
    "native": null,
    "timezone": "Europe/Rome",
    "translations": {}
  },
  {
    "id": 135750,
    "name": "Bagnara di Romagna",
    "state_id": 1707,
    "state_code": "RA",
    "country_id": 107,
    "country_code": "IT",
    "latitude": "44.38930000",
    "longitude": "11.82726000",
    "native": null,
    "timezone": "Europe/Rome",
    "translations": {}
  },
  {
    "id": 135830,
    "name": "Barbiano",
    "state_id": 1707,
    "state_code": "RA",
    "country_id": 107,
    "country_code": "IT",
    "latitude": "44.38950000",
    "longitude": "11.88650000",
    "native": null,
    "timezone": "Europe/Rome",
    "translations": {}
  },
  {
    "id": 136341,
    "name": "Brisighella",
    "state_id": 1707,
    "state_code": "RA",
    "country_id": 107,
    "country_code": "IT",
    "latitude": "44.22228000",
    "longitude": "11.77358000",
    "native": null,
    "timezone": "Europe/Rome",
    "translations": {}
  },
  {
    "id": 136381,
    "name": "Bubano",
    "state_id": 1707,
    "state_code": "RA",
    "country_id": 107,
    "country_code": "IT",
    "latitude": "44.41341000",
    "longitude": "11.78231000",
    "native": null,
    "timezone": "Europe/Rome",
    "translations": {}
  },
  {
    "id": 137078,
    "name": "Casola Valsenio",
    "state_id": 1707,
    "state_code": "RA",
    "country_id": 107,
    "country_code": "IT",
    "latitude": "44.22443000",
    "longitude": "11.62487000",
    "native": null,
    "timezone": "Europe/Rome",
    "translations": {}
  },
  {
    "id": 137131,
    "name": "Castel Bolognese",
    "state_id": 1707,
    "state_code": "RA",
    "country_id": 107,
    "country_code": "IT",
    "latitude": "44.31981000",
    "longitude": "11.79903000",
    "native": null,
    "timezone": "Europe/Rome",
    "translations": {}
  },
  {
    "id": 137591,
    "name": "Cervia",
    "state_id": 1707,
    "state_code": "RA",
    "country_id": 107,
    "country_code": "IT",
    "latitude": "44.26204000",
    "longitude": "12.34812000",
    "native": null,
    "timezone": "Europe/Rome",
    "translations": {}
  },
  {
    "id": 137806,
    "name": "Classe",
    "state_id": 1707,
    "state_code": "RA",
    "country_id": 107,
    "country_code": "IT",
    "latitude": "44.37955000",
    "longitude": "12.23654000",
    "native": null,
    "timezone": "Europe/Rome",
    "translations": {}
  },
  {
    "id": 137974,
    "name": "Conselice",
    "state_id": 1707,
    "state_code": "RA",
    "country_id": 107,
    "country_code": "IT",
    "latitude": "44.51163000",
    "longitude": "11.82848000",
    "native": null,
    "timezone": "Europe/Rome",
    "translations": {}
  },
  {
    "id": 138111,
    "name": "Cotignola",
    "state_id": 1707,
    "state_code": "RA",
    "country_id": 107,
    "country_code": "IT",
    "latitude": "44.38572000",
    "longitude": "11.93852000",
    "native": null,
    "timezone": "Europe/Rome",
    "translations": {}
  },
  {
    "id": 138403,
    "name": "Faenza",
    "state_id": 1707,
    "state_code": "RA",
    "country_id": 107,
    "country_code": "IT",
    "latitude": "44.29007000",
    "longitude": "11.87948000",
    "native": null,
    "timezone": "Europe/Rome",
    "translations": {}
  },
  {
    "id": 138577,
    "name": "Fognano",
    "state_id": 1707,
    "state_code": "RA",
    "country_id": 107,
    "country_code": "IT",
    "latitude": "44.20509000",
    "longitude": "11.73782000",
    "native": null,
    "timezone": "Europe/Rome",
    "translations": {}
  },
  {
    "id": 138644,
    "name": "Fornace Zarattini",
    "state_id": 1707,
    "state_code": "RA",
    "country_id": 107,
    "country_code": "IT",
    "latitude": "44.41667000",
    "longitude": "12.13333000",
    "native": null,
    "timezone": "Europe/Rome",
    "translations": {}
  },
  {
    "id": 138679,
    "name": "Fosso Ghiaia",
    "state_id": 1707,
    "state_code": "RA",
    "country_id": 107,
    "country_code": "IT",
    "latitude": "44.35525000",
    "longitude": "12.25430000",
    "native": null,
    "timezone": "Europe/Rome",
    "translations": {}
  },
  {
    "id": 138761,
    "name": "Fusignano",
    "state_id": 1707,
    "state_code": "RA",
    "country_id": 107,
    "country_code": "IT",
    "latitude": "44.46656000",
    "longitude": "11.95636000",
    "native": null,
    "timezone": "Europe/Rome",
    "translations": {}
  },
  {
    "id": 139006,
    "name": "Glorie",
    "state_id": 1707,
    "state_code": "RA",
    "country_id": 107,
    "country_code": "IT",
    "latitude": "44.46994000",
    "longitude": "12.07707000",
    "native": null,
    "timezone": "Europe/Rome",
    "translations": {}
  },
  {
    "id": 139009,
    "name": "Godo",
    "state_id": 1707,
    "state_code": "RA",
    "country_id": 107,
    "country_code": "IT",
    "latitude": "44.39173000",
    "longitude": "12.07495000",
    "native": null,
    "timezone": "Europe/Rome",
    "translations": {}
  },
  {
    "id": 139060,
    "name": "Granarolo",
    "state_id": 1707,
    "state_code": "RA",
    "country_id": 107,
    "country_code": "IT",
    "latitude": "44.35859000",
    "longitude": "11.93459000",
    "native": null,
    "timezone": "Europe/Rome",
    "translations": {}
  },
  {
    "id": 139414,
    "name": "Lavezzola",
    "state_id": 1707,
    "state_code": "RA",
    "country_id": 107,
    "country_code": "IT",
    "latitude": "44.56099000",
    "longitude": "11.87557000",
    "native": null,
    "timezone": "Europe/Rome",
    "translations": {}
  },
  {
    "id": 139502,
    "name": "Lido Adriano",
    "state_id": 1707,
    "state_code": "RA",
    "country_id": 107,
    "country_code": "IT",
    "latitude": "44.41673000",
    "longitude": "12.30552000",
    "native": null,
    "timezone": "Europe/Rome",
    "translations": {}
  },
  {
    "id": 139592,
    "name": "Longastrino",
    "state_id": 1707,
    "state_code": "RA",
    "country_id": 107,
    "country_code": "IT",
    "latitude": "44.58848000",
    "longitude": "12.00982000",
    "native": null,
    "timezone": "Europe/Rome",
    "translations": {}
  },
  {
    "id": 139648,
    "name": "Lugo",
    "state_id": 1707,
    "state_code": "RA",
    "country_id": 107,
    "country_code": "IT",
    "latitude": "44.42137000",
    "longitude": "11.91094000",
    "native": null,
    "timezone": "Europe/Rome",
    "translations": {}
  },
  {
    "id": 139709,
    "name": "Madonna Dell'Albero",
    "state_id": 1707,
    "state_code": "RA",
    "country_id": 107,
    "country_code": "IT",
    "latitude": "44.38115000",
    "longitude": "12.20044000",
    "native": null,
    "timezone": "Europe/Rome",
    "translations": {}
  },
  {
    "id": 139894,
    "name": "Marina di Ravenna",
    "state_id": 1707,
    "state_code": "RA",
    "country_id": 107,
    "country_code": "IT",
    "latitude": "44.48625000",
    "longitude": "12.28087000",
    "native": null,
    "timezone": "Europe/Rome",
    "translations": {}
  },
  {
    "id": 139873,
    "name": "Marina Romea",
    "state_id": 1707,
    "state_code": "RA",
    "country_id": 107,
    "country_code": "IT",
    "latitude": "44.51494000",
    "longitude": "12.27113000",
    "native": null,
    "timezone": "Europe/Rome",
    "translations": {}
  },
  {
    "id": 139971,
    "name": "Massa Lombarda",
    "state_id": 1707,
    "state_code": "RA",
    "country_id": 107,
    "country_code": "IT",
    "latitude": "44.44703000",
    "longitude": "11.82095000",
    "native": null,
    "timezone": "Europe/Rome",
    "translations": {}
  },
  {
    "id": 140112,
    "name": "Mezzano",
    "state_id": 1707,
    "state_code": "RA",
    "country_id": 107,
    "country_code": "IT",
    "latitude": "44.46625000",
    "longitude": "12.08632000",
    "native": null,
    "timezone": "Europe/Rome",
    "translations": {}
  },
  {
    "id": 140144,
    "name": "Milano Marittima",
    "state_id": 1707,
    "state_code": "RA",
    "country_id": 107,
    "country_code": "IT",
    "latitude": "44.27409000",
    "longitude": "12.35172000",
    "native": null,
    "timezone": "Europe/Rome",
    "translations": {}
  },
  {
    "id": 58533,
    "name": "Piangipane",
    "state_id": 1707,
    "state_code": "RA",
    "country_id": 107,
    "country_code": "IT",
    "latitude": "44.42198000",
    "longitude": "12.09066000",
    "native": null,
    "timezone": "Europe/Rome",
    "translations": {}
  },
  {
    "id": 58671,
    "name": "Pinarella",
    "state_id": 1707,
    "state_code": "RA",
    "country_id": 107,
    "country_code": "IT",
    "latitude": "44.24167000",
    "longitude": "12.37111000",
    "native": null,
    "timezone": "Europe/Rome",
    "translations": {}
  },
  {
    "id": 58927,
    "name": "Porto Corsini",
    "state_id": 1707,
    "state_code": "RA",
    "country_id": 107,
    "country_code": "IT",
    "latitude": "44.49410000",
    "longitude": "12.27875000",
    "native": null,
    "timezone": "Europe/Rome",
    "translations": {}
  },
  {
    "id": 58930,
    "name": "Porto Fuori",
    "state_id": 1707,
    "state_code": "RA",
    "country_id": 107,
    "country_code": "IT",
    "latitude": "44.40557000",
    "longitude": "12.25218000",
    "native": null,
    "timezone": "Europe/Rome",
    "translations": {}
  },
  {
    "id": 59205,
    "name": "Punta Marina",
    "state_id": 1707,
    "state_code": "RA",
    "country_id": 107,
    "country_code": "IT",
    "latitude": "44.44272000",
    "longitude": "12.29089000",
    "native": null,
    "timezone": "Europe/Rome",
    "translations": {}
  },
  {
    "id": 59299,
    "name": "Ravenna",
    "state_id": 1707,
    "state_code": "RA",
    "country_id": 107,
    "country_code": "IT",
    "latitude": "44.41344000",
    "longitude": "12.20121000",
    "native": null,
    "timezone": "Europe/Rome",
    "translations": {}
  },
  {
    "id": 59393,
    "name": "Riolo Terme",
    "state_id": 1707,
    "state_code": "RA",
    "country_id": 107,
    "country_code": "IT",
    "latitude": "44.27609000",
    "longitude": "11.72722000",
    "native": null,
    "timezone": "Europe/Rome",
    "translations": {}
  },
  {
    "id": 59704,
    "name": "Russi",
    "state_id": 1707,
    "state_code": "RA",
    "country_id": 107,
    "country_code": "IT",
    "latitude": "44.37645000",
    "longitude": "12.03335000",
    "native": null,
    "timezone": "Europe/Rome",
    "translations": {}
  },
  {
    "id": 60150,
    "name": "San Pancrazio",
    "state_id": 1707,
    "state_code": "RA",
    "country_id": 107,
    "country_code": "IT",
    "latitude": "44.35810000",
    "longitude": "12.07852000",
    "native": null,
    "timezone": "Europe/Rome",
    "translations": {}
  },
  {
    "id": 60178,
    "name": "San Pietro In Vincoli",
    "state_id": 1707,
    "state_code": "RA",
    "country_id": 107,
    "country_code": "IT",
    "latitude": "44.30051000",
    "longitude": "12.14556000",
    "native": null,
    "timezone": "Europe/Rome",
    "translations": {}
  },
  {
    "id": 60326,
    "name": "Sant'Agata sul Santerno",
    "state_id": 1707,
    "state_code": "RA",
    "country_id": 107,
    "country_code": "IT",
    "latitude": "44.44351000",
    "longitude": "11.86112000",
    "native": null,
    "timezone": "Europe/Rome",
    "translations": {}
  },
  {
    "id": 60330,
    "name": "Sant'Alberto",
    "state_id": 1707,
    "state_code": "RA",
    "country_id": 107,
    "country_code": "IT",
    "latitude": "44.53822000",
    "longitude": "12.16191000",
    "native": null,
    "timezone": "Europe/Rome",
    "translations": {}
  },
  {
    "id": 60507,
    "name": "Santerno",
    "state_id": 1707,
    "state_code": "RA",
    "country_id": 107,
    "country_code": "IT",
    "latitude": "44.43697000",
    "longitude": "12.05533000",
    "native": null,
    "timezone": "Europe/Rome",
    "translations": {}
  },
  {
    "id": 60527,
    "name": "Santo Stefano-Carraie",
    "state_id": 1707,
    "state_code": "RA",
    "country_id": 107,
    "country_code": "IT",
    "latitude": "44.31525000",
    "longitude": "12.18573000",
    "native": null,
    "timezone": "Europe/Rome",
    "translations": {}
  },
  {
    "id": 60584,
    "name": "Savarna-Conventello",
    "state_id": 1707,
    "state_code": "RA",
    "country_id": 107,
    "country_code": "IT",
    "latitude": "44.50717000",
    "longitude": "12.10621000",
    "native": null,
    "timezone": "Europe/Rome",
    "translations": {}
  },
  {
    "id": 60593,
    "name": "Savio",
    "state_id": 1707,
    "state_code": "RA",
    "country_id": 107,
    "country_code": "IT",
    "latitude": "44.31139000",
    "longitude": "12.29472000",
    "native": null,
    "timezone": "Europe/Rome",
    "translations": {}
  },
  {
    "id": 60798,
    "name": "Sesto Imolese",
    "state_id": 1707,
    "state_code": "RA",
    "country_id": 107,
    "country_code": "IT",
    "latitude": "44.45952000",
    "longitude": "11.72919000",
    "native": null,
    "timezone": "Europe/Rome",
    "translations": {}
  },
  {
    "id": 60905,
    "name": "Solarolo",
    "state_id": 1707,
    "state_code": "RA",
    "country_id": 107,
    "country_code": "IT",
    "latitude": "44.35892000",
    "longitude": "11.84661000",
    "native": null,
    "timezone": "Europe/Rome",
    "translations": {}
  },
  {
    "id": 62217,
    "name": "Voltana",
    "state_id": 1707,
    "state_code": "RA",
    "country_id": 107,
    "country_code": "IT",
    "latitude": "44.54109000",
    "longitude": "11.93533000",
    "native": null,
    "timezone": "Europe/Rome",
    "translations": {}
  }
]